{
  "id": "meditacao-autoafirmativa",
  "tipo": "poder",
  "nome": "Meditação Autoafirmativa",
  "fonte": {
    "livro": "herois-de-arton",
    "pagina": 80
  },
  "imagens": [],
  "secoes": [],
  "relacoes": [],
  "mecanica": {
    "grupo": "destino",
    "prerequisito": "Sab 1, Car 1, 5º nível de personagem",
    "descricao": "Você pode entrar em um transe hipnótico no qual convence a si mesmo de que possui certas habilidades. Para usar este poder, você deve escolher um benefício da tabela abaixo e meditar por 1 dia. No fim do dia, faça um teste de Carisma (CD conforme o benefício escolhido). Se passar, você adquire esse benefício por uma semana ou até usar este poder novamente.\n\nBenefício                                                    | CD\n\"Eu sei lutar.\" +1 em testes de ataque                       | 15\n\"Eu sei lutar muito bem.\" +2 em testes de ataque            | 20\n\"Por Anilatir, como eu luto bem!\" +3 em testes de ataque    | 25\n\"Ninguém toca em mim.\" +2 na Defesa                         | 20\n\"Nada me afeta.\" +5 em testes de resistência                | 20\n\"Eu sei fazer isso.\" Torna-se treinado em uma perícia        | 17\n\"Eu sou bom demais!\" Pode usar um poder cujos pré-requisitos você cumpra | 22\n\nEnquanto medita, você fica fascinado. Você pode meditar por mais de um dia; nesse caso, cada dia fornece um bônus de +1 no teste de Carisma, até um máximo de +7 para uma semana. Mestres malvados podem exigir testes de Fortitude para personagens que passem vários dias sem se alimentar (veja \"Fome e Sede\", Tormenta20, p. 319)."
  }
}