{"id":"cavalo-de-carga","tipo":"criatura","nome":"Cavalo de Carga","resumo":"Cavalo mais lento e robusto, próprio para puxar arados, transportar carga e mover carroças pesadas.","fonte":{"livro":"ameacas-de-arton","pagina":212},"imagens":[],"secoes":[{"titulo":"","texto":"Mais lento, mas também mais forte, este animal robusto é próprio para puxar arados, transportar alforjes cheios no lombo ou mover carroças pesadas. Seja a galope ou em viagens longas, tem a mesma velocidade média de um humano."}],"relacoes":[],"mecanica":{"nd":"1/2","tipo":"Animal","tamanho":"Grande","tema":"Montarias","iniciativa":"+2","percepcao":"+5, faro, visão na penumbra","defesa":"12","fortitude":"+6","reflexos":"+0","vontade":"+3","pontosDeVida":"27","deslocamento":"9m (6q)","ataques":["Corpo a Corpo Cascos +7 (2d4+5)."],"atributos":{"forca":"5","destreza":"0","constituicao":"3","inteligencia":"–4","sabedoria":"1","carisma":"–2"},"pericias":"Atletismo +9.","tesouro":"Nenhum.","habilidades":[{"nome":"Parceiro","descricao":"O cavalo de carga é um parceiro besta de carga (veja a página 416)."}]}}
