{"id":"mashin-monge","tipo":"criatura","nome":"Mashin Monge","resumo":"Golem tamuraniano ágil e disciplinado, que canaliza energia elemental de frio em seus golpes desarmados.","fonte":{"livro":"ameacas-de-arton","pagina":160},"imagens":[],"secoes":[{"titulo":"","texto":"Mashin são golens de origem tamuraniana, tão belos que são considerados obras de arte, tão sofisticados que igualam os humanos em qualquer tarefa. Todos têm inteligência, vontade própria e são reconhecidos como cidadãos no Império de Jade."}],"relacoes":[{"tipo":"versaoJogavel","alvoId":"mashin","alvoTipo":"raca","rotulo":"Versão jogável"}],"mecanica":{"nd":"3","tipo":"Construto (golem)","tamanho":"Médio","tema":"Império de Jade","iniciativa":"+7","percepcao":"+3, visão no escuro","defesa":"22, evasão, imunidade a frio","fortitude":"+4","reflexos":"+15","vontade":"+10","pontosDeVida":"135","deslocamento":"12m (8q)","ataques":["Corpo a Corpo Ataque desarmado x3 +15 (1d6+4).","À Distância Adaga +13 (1d4+4, 19)."],"atributos":{"forca":"3","destreza":"4","constituicao":"3","inteligencia":"0","sabedoria":"3","carisma":"0"},"pericias":"Acrobacia +7, Atletismo +6, Cura +6, Religião +6.","equipamento":"Adaga x3.","tesouro":"Nenhum.","habilidades":[{"nome":"Arma Elemental (Movimento)","descricao":"Até o fim da rodada, o mashin monge causa +1d6 pontos de dano de frio com seus ataques."},{"nome":"Ataque de Chi","descricao":"Os ataques desarmados do monge ignoram 5 pontos de redução de dano."}]}}
