{
  "id": "colar-do-tirano",
  "tipo": "item-magico",
  "nome": "Colar do Tirano",
  "resumo": "Item cruel de abissais que permite causar dano a escravos encoleirados e vincula danos sofridos pelo usuário aos escravizados.",
  "fonte": { "livro": "herois-de-arton", "pagina": 265 },
  "imagens": [],
  "relacoes": [],
  "secoes": [
    {
      "titulo": "Descrição",
      "texto": "Este item cruel é fabricado por abissais e usado por escravagistas. Cada colar tem conexão planar com uma ou mais coleiras (tipicamente 1d8) destinadas a prisioneiros escravizados. Uma vez por rodada, o usuário do colar do tirano pode causar 2d8+2 pontos de dano de eletricidade a um escravo encoleirado. Tentativas mundanas de remover a coleira causam o mesmo dano — apenas efeitos como Dissipar Magia permitem destrancá-las. Além disso, qualquer dano ou efeito nocivo causado ao usuário do colar também afeta todos os escravos encoleirados."
    }
  ],
  "mecanica": {
    "tipoItem": "Acessório",
    "categoria": "Média",
    "preco": "T$ 10.500"
  }
}
